swaguard/__init__.py
swaguard/config.py
swaguard/core/__init__.py
swaguard/core/auth.py
swaguard/core/security.py
swaguard/decorators/__init__.py
swaguard/decorators/fastapi.py
swaguard/exceptions/AuthExceptions.py
swaguard/exceptions/__init__.py
swaguard/middlewares/__init__.py
swaguard/middlewares/fastapi_mw.py
swaguard/routes/__init__.py
swaguard/routes/login_route.py
swaguard/tests/__init__.py
swaguard/tests/test_auth.py
swaguard/utils/__init__.py
swaguard/utils/helper.py
swaguard-0.1.0.dist-info/licenses/LICENSE
swaguard-0.1.0.dist-info/METADATA
swaguard-0.1.0.dist-info/WHEEL
swaguard-0.1.0.dist-info/top_level.txt
swaguard-0.1.0.dist-info/RECORD
