Metadata-Version: 2.4
Name: swaguard
Version: 0.1.0
Summary: A library to protect Swagger/OpenAPI UI in FastAPI and Django applications
Home-page: https://github.com/riseryan89/swaguard
Author: Ryan
Author-email: rise.ryan.lee@gmail.com
Classifier: Programming Language :: Python :: 3
Classifier: License :: OSI Approved :: MIT License
Classifier: Operating System :: OS Independent
Classifier: Framework :: FastAPI
Classifier: Framework :: Django
Classifier: Topic :: Software Development :: Libraries :: Python Modules
Requires-Python: >=3.6
License-File: LICENSE
Requires-Dist: fastapi>=0.70.0
Requires-Dist: pydantic>=1.8.0
Requires-Dist: python-multipart>=0.0.5
Requires-Dist: pyyaml>=5.1
Requires-Dist: bcrypt>=3.2.0
Provides-Extra: dev
Requires-Dist: pytest>=6.0.0; extra == "dev"
Requires-Dist: uvicorn>=0.15.0; extra == "dev"
Dynamic: author
Dynamic: author-email
Dynamic: classifier
Dynamic: description
Dynamic: description-content-type
Dynamic: home-page
Dynamic: license-file
Dynamic: provides-extra
Dynamic: requires-dist
Dynamic: requires-python
Dynamic: summary
